syntheval/__init__.py
syntheval/__main__.py
syntheval/syntheval.py
syntheval/metrics/__init__.py
syntheval/metrics/metric_template.py
syntheval/metrics/core/__init__.py
syntheval/metrics/core/metric.py
syntheval/metrics/fairness/metric_statistical_parity.py
syntheval/metrics/privacy/metric_AttrDis.py
syntheval/metrics/privacy/metric_MIA_classification.py
syntheval/metrics/privacy/metric_distance_closest_record.py
syntheval/metrics/privacy/metric_epsilon_identifiability.py
syntheval/metrics/privacy/metric_hitting_rate.py
syntheval/metrics/privacy/metric_nn_adversarial_accuracy.py
syntheval/metrics/privacy/metric_nn_distance_ratio.py
syntheval/metrics/utility/metric_accuracy_difference.py
syntheval/metrics/utility/metric_auroc_difference.py
syntheval/metrics/utility/metric_confidence_interval_overlap.py
syntheval/metrics/utility/metric_dimensionwise_means.py
syntheval/metrics/utility/metric_hellinger_distance.py
syntheval/metrics/utility/metric_kolmogorov_smirnov.py
syntheval/metrics/utility/metric_mixed_correlation.py
syntheval/metrics/utility/metric_mutual_information.py
syntheval/metrics/utility/metric_principal_component_analysis.py
syntheval/metrics/utility/metric_propensity_mse.py
syntheval/metrics/utility/metric_quantile_mse.py
syntheval/presets/fast_eval.json
syntheval/presets/full_eval.json
syntheval/presets/privacy.json
syntheval/utils/console_output.py
syntheval/utils/nn_distance.py
syntheval/utils/plot_metrics.py
syntheval/utils/postprocessing.py
syntheval/utils/preprocessing.py
syntheval/utils/variable_detection.py
syntheval-1.6.2.dist-info/METADATA
syntheval-1.6.2.dist-info/WHEEL
syntheval-1.6.2.dist-info/entry_points.txt
syntheval-1.6.2.dist-info/licenses/LICENSE
syntheval-1.6.2.dist-info/RECORD
