Metadata-Version: 2.4
Name: syntheval
Version: 1.6.2
Summary: A package for evaluating synthetic data fidelity on various performance dimensions.
Project-URL: Homepage, https://github.com/schneiderkamplab/syntheval
Project-URL: Bug Tracker, https://github.com/schneiderkamplab/syntheval/issues
Author: Anton D. Lautrup, Tobias Hyrup, Muhammad Rajabinasab, Peter Schneider-Kamp
License-File: LICENSE
Classifier: License :: OSI Approved :: MIT License
Classifier: Operating System :: OS Independent
Classifier: Programming Language :: Python :: 3
Requires-Python: >=3.9
Requires-Dist: click>=8.1.3
Requires-Dist: lightgbm
Requires-Dist: matplotlib
Requires-Dist: numpy~=1.26
Requires-Dist: pandas
Requires-Dist: pcametric~=1.0.3
Requires-Dist: scikit-learn>=1.2
Requires-Dist: scipy>=1.14.1
Requires-Dist: seaborn
Requires-Dist: tqdm
